MarchMadness/AIWeighting.py
MarchMadness/MarchMadness.py
MarchMadness/MarchMadnessRun.py
MarchMadness/Simulate.py
MarchMadness/__init__.py
MarchMadness/bracket.py
MarchMadness/Brackets/2013bracket1.jpg
MarchMadness/Brackets/2013bracket10.jpg
MarchMadness/Brackets/2013bracket11.jpg
MarchMadness/Brackets/2013bracket12.jpg
MarchMadness/Brackets/2013bracket13.jpg
MarchMadness/Brackets/2013bracket14.jpg
MarchMadness/Brackets/2013bracket15.jpg
MarchMadness/Brackets/2013bracket16.jpg
MarchMadness/Brackets/2013bracket17.jpg
MarchMadness/Brackets/2013bracket18.jpg
MarchMadness/Brackets/2013bracket19.jpg
MarchMadness/Brackets/2013bracket2.jpg
MarchMadness/Brackets/2013bracket20.jpg
MarchMadness/Brackets/2013bracket3.jpg
MarchMadness/Brackets/2013bracket4.jpg
MarchMadness/Brackets/2013bracket5.jpg
MarchMadness/Brackets/2013bracket6.jpg
MarchMadness/Brackets/2013bracket7.jpg
MarchMadness/Brackets/2013bracket8.jpg
MarchMadness/Brackets/2013bracket9.jpg
MarchMadness/Brackets/__init__.py
MarchMadness/Previous/DejaVuSerif-Bold.ttf
MarchMadness/Previous/MMadnessBoxScores_15-19.csv
MarchMadness/Previous/NCAATourneyFullBoxscoresAndStats_15-19.csv
MarchMadness/Previous/NCAATourneyGamesAndSeasonStats_15-19.csv
MarchMadness/Previous/__init__.py
MarchMadness/Previous/bracket13.txt
MarchMadness/Previous/bracket14.txt
MarchMadness/Previous/bracket19.txt
MarchMadness/Previous/bracket21.txt
MarchMadness/Previous/bracket22.txt
MarchMadness/Previous/cbb.csv
MarchMadness/Previous/cbb13.csv
MarchMadness/Previous/cbb14.csv
MarchMadness/Previous/cbb15.csv
MarchMadness/Previous/cbb16.csv
MarchMadness/Previous/cbb17.csv
MarchMadness/Previous/cbb18.csv
MarchMadness/Previous/cbb19.csv
MarchMadness/Previous/cbb20.csv
MarchMadness/Previous/cbb21.csv
MarchMadness/Previous/example.txt
MarchMadness/Previous/teams13.txt
MarchMadness/Previous/teams14.txt
MarchMadness/Previous/teams15.txt
MarchMadness/Previous/teams16.txt
MarchMadness/Previous/teams17.txt
MarchMadness/Previous/teams18.txt
MarchMadness-1.6.0.dist-info/LICENSE
MarchMadness-1.6.0.dist-info/METADATA
MarchMadness-1.6.0.dist-info/WHEEL
MarchMadness-1.6.0.dist-info/top_level.txt
MarchMadness-1.6.0.dist-info/RECORD
