Metadata-Version: 2.1
Name: MarchMadness
Version: 1.6.0
Summary: March Madness bracket simulation 2022
Home-page: https://github.com/thalper/March-Madness
Author: Tycho Halpern, Rylee Benes, Luca Rivera
Author-email: thalper@purdue.edu, rbenes@purdue.edu, river172@purdue.edu
License: MIT
Platform: UNKNOWN
Classifier: Programming Language :: Python :: 3
Requires-Dist: coverage
Requires-Dist: importlib-resources
Requires-Dist: mypy
Requires-Dist: numpy
Requires-Dist: opencv-python
Requires-Dist: pillow
Requires-Dist: pytest
Requires-Dist: pytest-cov
Requires-Dist: regex
Requires-Dist: scikit-learn
